pts_keysight_dmm/__init__.py
pts_keysight_dmm/keysight_dmm.py
pts_keysight_dmm-0.0.10.dist-info/LICENSE.txt
pts_keysight_dmm-0.0.10.dist-info/METADATA
pts_keysight_dmm-0.0.10.dist-info/WHEEL
pts_keysight_dmm-0.0.10.dist-info/top_level.txt
pts_keysight_dmm-0.0.10.dist-info/RECORD
