Metadata-Version: 2.1
Name: pts-keysight-dmm
Version: 0.0.10
Summary: Keysight DMM 34465A Diagnostic Package
Home-page: https://gitlab.com/pass-testing-solutions/keysight34465a-interface
Author: Pass testing Solutions GmbH
Author-email: shuparna@pass-testing.de
License: MIT
Platform: UNKNOWN
Classifier: License :: OSI Approved :: MIT License
Classifier: Programming Language :: Python :: 3
Classifier: Programming Language :: Python :: 3.9
License-File: LICENSE.txt
Requires-Dist: RsInstrument (~=1.24.0.83)
Requires-Dist: pyvisa
Requires-Dist: pyvisa-py
